Workbook

Sheet PARAMETROS
B2: MODELO DE AMORTIZACIÓN FINANCIERA — PARÁMETROS
B3: Proyección patrimonial mensual — celdas azules = editables. Modifica cualquier supuesto y todo el modelo se recalcula.
B5: 1. DATOS INICIALES DEL HORIZONTE
B6: Edad inicial (años) | C6: 65
B7: Edad final (años) | C7: 95
B8: Capital inicial (MXN) | C8: 1000000
B9: Pensión mensual inicial (MXN) | C9: 30000
B10: Gasto mensual inicial (MXN) | C10: 32000
B12: 2. DISTRIBUCIÓN DEL GASTO (editable)
B13: % Gasto médico | C13: 0.2
B14: % Gasto general | C14: =1-C13 -> 0.8
B16: 3. SUPUESTOS ANUALES (editable)
B17: INPC anual (actualiza pensión, 1 vez/año) | C17: 0.0394
B18: Inflación subyacente anual (gasto general) | C18: 0.0419
B19: Inflación médica anual (gasto médico) | C19: 0.0484
B20: CETES 28 días anual (rendimiento) | C20: 0.0611
B21: Retención fiscal inversión anual | C21: 0.009
B23: 4. AGING FACTOR — GASTO MÉDICO (editable)
B24: Aging 65–69 años (anual) | C24: 0.03
B25: Aging 70–74 años (anual) | C25: 0.025
B26: Aging 75–79 años (anual) | C26: 0.02
B27: Aging 80–84 años (anual) | C27: 0.01
B28: Aging 85–89 años (anual) | C28: 0.005
B29: Aging 90+ años (anual) | C29: 0
B30: Nota: estos son SUPUESTOS para el modelo determinístico, no predicciones oficiales.
B32: 5. VALORES CALCULADOS AUTOMÁTICAMENTE
B33: Número de meses del horizonte | C33: =(C7-C6)*12 -> 360
B34: Gasto médico inicial (MXN) | C34: =C10*C13 -> 6400
B35: Gasto general inicial (MXN) | C35: =C10*C14 -> 25600
B36: Inflación subyacente mensual | C36: =(1+C18)^(1/12)-1 -> 0.003426354
B37: Inflación médica mensual | C37: =(1+C19)^(1/12)-1 -> 0.0039465332
B38: CETES mensual | C38: =(1+C20)^(1/12)-1 -> 0.0049544082
B39: Retención fiscal mensual equiv. | C39: =(1+C21)^(1/12)-1 -> 0.00074692392
B40: Aging 65–69 mensual | C40: =(1+C24)^(1/12)-1 -> 0.0024662698
B41: Aging 70–74 mensual | C41: =(1+C25)^(1/12)-1 -> 0.0020598363
B42: Aging 75–79 mensual | C42: =(1+C26)^(1/12)-1 -> 0.0016515813
B43: Aging 80–84 mensual | C43: =(1+C27)^(1/12)-1 -> 0.00082953811
B44: Aging 85–89 mensual | C44: =(1+C28)^(1/12)-1 -> 0.00041571484
B45: Aging 90+ mensual | C45: =(1+C29)^(1/12)-1 -> 0
B47: IMPORTANTE: fila 33 (número de meses) alimenta automáticamente el número de filas activas en la hoja AMORTIZACION (máx. soportado 720 meses / 60 años). Las filas de AMORTIZACION más allá del horizonte activo se muestran en blanco.

Sheet AMORTIZACION
A1: AMORTIZACIÓN MENSUAL — 1 fila por mes (auto-generada según PARAMETROS!C6:C7)
A2: Mes | B2: Año proy. | C2: Edad | D2: Mes en edad | E2: Saldo inicial | F2: Tasa CETES mens. | G2: Rend. CETES | H2: Retención inv. | I2: Rend. neto | J2: Pensión mensual | K2: Gasto general | L2: Gasto médico | M2: Aging médico (tasa mens.) | N2: Gasto total | O2: Flujo neto | P2: Saldo final | Q2: Estado
A3: 1 | B3: =IF($A3="","",ROUNDUP($A3/12,0)) -> 1 | C3: =IF($A3="","",PARAMETROS!$C$6+INT(($A3-1)/12)) -> 65 | D3: =IF($A3="","",MOD($A3-1,12)+1) -> 1 | E3: =PARAMETROS!$C$8 -> 1000000 | F3: =IF($A3>PARAMETROS!$C$33,"",PARAMETROS!$C$38) -> 0.0049544082 | G3: =IF($A3>PARAMETROS!$C$33,"",E3*F3) -> 4954.4082 | H3: =IF($A3>PARAMETROS!$C$33,"",E3*PARAMETROS!$C$39) -> 746.92392 | I3: =IF($A3>PARAMETROS!$C$33,"",G3-H3) -> 4207.4843 | J3: =IF($A3>PARAMETROS!$C$33,"",PARAMETROS!$C$9*(1+PARAMETROS!$C$17)^(B3-1)) -> 30000 | K3: =PARAMETROS!$C$35 -> 25600 | L3: =PARAMETROS!$C$34 -> 6400 | M3: =IF($A3>PARAMETROS!$C$33,"",IF(C3<70,PARAMETROS!$C$40,IF(C3<75,PARAMETROS!$C$41,IF(C3<80,PARAMETROS!$C$42,IF(C3<85,PARAMETROS!$C$43,IF(C3<90,PARAMETROS!$C$44,PARAMETROS!$C$45)))))) -> 0.0024662698 | N3: =IF($A3>PARAMETROS!$C$33,"",K3+L3) -> 32000 | O3: =IF($A3>PARAMETROS!$C$33,"",I3+J3-N3) -> 2207.4843 | P3: =IF($A3>PARAMETROS!$C$33,"",MAX(E3+I3+J3-N3,0)) -> 1002207.5 | Q3: =IF($A3>PARAMETROS!$C$33,"",IF(P3<=0,"AGOTADO","OK")) -> OK
A4: =A3+1 -> 2 | B4: =IF($A4="","",ROUNDUP($A4/12,0)) -> 1 | C4: =IF($A4="","",PARAMETROS!$C$6+INT(($A4-1)/12)) -> 65 | D4: =IF($A4="","",MOD($A4-1,12)+1) -> 2 | E4: =IF($A4>PARAMETROS!$C$33,"",P3) -> 1002207.5 | F4: =IF($A4>PARAMETROS!$C$33,"",PARAMETROS!$C$38) -> 0.0049544082 | G4: =IF($A4>PARAMETROS!$C$33,"",E4*F4) -> 4965.345 | H4: =IF($A4>PARAMETROS!$C$33,"",E4*PARAMETROS!$C$39) -> 748.57275 | I4: =IF($A4>PARAMETROS!$C$33,"",G4-H4) -> 4216.7722 | J4: =IF($A4>PARAMETROS!$C$33,"",PARAMETROS!$C$9*(1+PARAMETROS!$C$17)^(B4-1)) -> 30000 | K4: =IF($A4>PARAMETROS!$C$33,"",K3*(1+PARAMETROS!$C$36)) -> 25687.715 | L4: =IF($A4>PARAMETROS!$C$33,"",L3*(1+PARAMETROS!$C$37)*(1+M4)) -> 6441.1042 | M4: =IF($A4>PARAMETROS!$C$33,"",IF(C4<70,PARAMETROS!$C$40,IF(C4<75,PARAMETROS!$C$41,IF(C4<80,PARAMETROS!$C$42,IF(C4<85,PARAMETROS!$C$43,IF(C4<90,PARAMETROS!$C$44,PARAMETROS!$C$45)))))) -> 0.0024662698 | N4: =IF($A4>PARAMETROS!$C$33,"",K4+L4) -> 32128.819 | O4: =IF($A4>PARAMETROS!$C$33,"",I4+J4-N4) -> 2087.9533 | P4: =IF($A4>PARAMETROS!$C$33,"",MAX(E4+I4+J4-N4,0)) -> 1004295.4 | Q4: =IF($A4>PARAMETROS!$C$33,"",IF(P4<=0,"AGOTADO","OK")) -> OK
A5: =A4+1 -> 3 | B5: =IF($A5="","",ROUNDUP($A5/12,0)) -> 1 | C5: =IF($A5="","",PARAMETROS!$C$6+INT(($A5-1)/12)) -> 65 | D5: =IF($A5="","",MOD($A5-1,12)+1) -> 3 | E5: =IF($A5>PARAMETROS!$C$33,"",P4) -> 1004295.4 | F5: =IF($A5>PARAMETROS!$C$33,"",PARAMETROS!$C$38) -> 0.0049544082 | G5: =IF($A5>PARAMETROS!$C$33,"",E5*F5) -> 4975.6895 | H5: =IF($A5>PARAMETROS!$C$33,"",E5*PARAMETROS!$C$39) -> 750.13229 | I5: =IF($A5>PARAMETROS!$C$33,"",G5-H5) -> 4225.5572 | J5: =IF($A5>PARAMETROS!$C$33,"",PARAMETROS!$C$9*(1+PARAMETROS!$C$17)^(B5-1)) -> 30000 | K5: =IF($A5>PARAMETROS!$C$33,"",K4*(1+PARAMETROS!$C$36)) -> 25775.73 | L5: =IF($A5>PARAMETROS!$C$33,"",L4*(1+PARAMETROS!$C$37)*(1+M5)) -> 6482.4725 | M5: =IF($A5>PARAMETROS!$C$33,"",IF(C5<70,PARAMETROS!$C$40,IF(C5<75,PARAMETROS!$C$41,IF(C5<80,PARAMETROS!$C$42,IF(C5<85,PARAMETROS!$C$43,IF(C5<90,PARAMETROS!$C$44,PARAMETROS!$C$45)))))) -> 0.0024662698 | N5: =IF($A5>PARAMETROS!$C$33,"",K5+L5) -> 32258.202 | O5: =IF($A5>PARAMETROS!$C$33,"",I5+J5-N5) -> 1967.3549 | P5: =IF($A5>PARAMETROS!$C$33,"",MAX(E5+I5+J5-N5,0)) -> 1006262.8 | Q5: =IF($A5>PARAMETROS!$C$33,"",IF(P5<=0,"AGOTADO","OK")) -> OK
A6: =A5+1 -> 4 | B6: =IF($A6="","",ROUNDUP($A6/12,0)) -> 1 | C6: =IF($A6="","",PARAMETROS!$C$6+INT(($A6-1)/12)) -> 65 | D6: =IF($A6="","",MOD($A6-1,12)+1) -> 4 | E6: =IF($A6>PARAMETROS!$C$33,"",P5) -> 1006262.8 | F6: =IF($A6>PARAMETROS!$C$33,"",PARAMETROS!$C$38) -> 0.0049544082 | G6: =IF($A6>PARAMETROS!$C$33,"",E6*F6) -> 4985.4366 | H6: =IF($A6>PARAMETROS!$C$33,"",E6*PARAMETROS!$C$39) -> 751.60175 | I6: =IF($A6>PARAMETROS!$C$33,"",G6-H6) -> 4233.8349 | J6: =IF($A6>PARAMETROS!$C$33,"",PARAMETROS!$C$9*(1+PARAMETROS!$C$17)^(B6-1)) -> 30000 | K6: =IF($A6>PARAMETROS!$C$33,"",K5*(1+PARAMETROS!$C$36)) -> 25864.047 | L6: =IF($A6>PARAMETROS!$C$33,"",L5*(1+PARAMETROS!$C$37)*(1+M6)) -> 6524.1064 | M6: =IF($A6>PARAMETROS!$C$33,"",IF(C6<70,PARAMETROS!$C$40,IF(C6<75,PARAMETROS!$C$41,IF(C6<80,PARAMETROS!$C$42,IF(C6<85,PARAMETROS!$C$43,IF(C6<90,PARAMETROS!$C$44,PARAMETROS!$C$45)))))) -> 0.0024662698 | N6: =IF($A6>PARAMETROS!$C$33,"",K6+L6) -> 32388.153 | O6: =IF($A6>PARAMETROS!$C$33,"",I6+J6-N6) -> 1845.6818 | P6: =IF($A6>PARAMETROS!$C$33,"",MAX(E6+I6+J6-N6,0)) -> 1008108.5 | Q6: =IF($A6>PARAMETROS!$C$33,"",IF(P6<=0,"AGOTADO","OK")) -> OK
A7: =A6+1 -> 5 | B7: =IF($A7="","",ROUNDUP($A7/12,0)) -> 1 | C7: =IF($A7="","",PARAMETROS!$C$6+INT(($A7-1)/12)) -> 65 | D7: =IF($A7="","",MOD($A7-1,12)+1) -> 5 | E7: =IF($A7>PARAMETROS!$C$33,"",P6) -> 1008108.5 | F7: =IF($A7>PARAMETROS!$C$33,"",PARAMETROS!$C$38) -> 0.0049544082 | G7: =IF($A7>PARAMETROS!$C$33,"",E7*F7) -> 4994.5809 | H7: =IF($A7>PARAMETROS!$C$33,"",E7*PARAMETROS!$C$39) -> 752.98034 | I7: =IF($A7>PARAMETROS!$C$33,"",G7-H7) -> 4241.6005 | J7: =IF($A7>PARAMETROS!$C$33,"",PARAMETROS!$C$9*(1+PARAMETROS!$C$17)^(B7-1)) -> 30000 | K7: =IF($A7>PARAMETROS!$C$33,"",K6*(1+PARAMETROS!$C$36)) -> 25952.666 | L7: =IF($A7>PARAMETROS!$C$33,"",L6*(1+PARAMETROS!$C$37)*(1+M7)) -> 6566.0077 | M7: =IF($A7>PARAMETROS!$C$33,"",IF(C7<70,PARAMETROS!$C$40,IF(C7<75,PARAMETROS!$C$41,IF(C7<80,PARAMETROS!$C$42,IF(C7<85,PARAMETROS!$C$43,IF(C7<90,PARAMETROS!$C$44,PARAMETROS!$C$45)))))) -> 0.0024662698 | N7: =IF($A7>PARAMETROS!$C$33,"",K7+L7) -> 32518.674 | O7: =IF($A7>PARAMETROS!$C$33,"",I7+J7-N7) -> 1722.9268 | P7: =IF($A7>PARAMETROS!$C$33,"",MAX(E7+I7+J7-N7,0)) -> 1009831.4 | Q7: =IF($A7>PARAMETROS!$C$33,"",IF(P7<=0,"AGOTADO","OK")) -> OK
A8: =A7+1 -> 6 | B8: =IF($A8="","",ROUNDUP($A8/12,0)) -> 1 | C8: =IF($A8="","",PARAMETROS!$C$6+INT(($A8-1)/12)) -> 65 | D8: =IF($A8="","",MOD($A8-1,12)+1) -> 6 | E8: =IF($A8>PARAMETROS!$C$33,"",P7) -> 1009831.4 | F8: =IF($A8>PARAMETROS!$C$33,"",PARAMETROS!$C$38) -> 0.0049544082 | G8: =IF($A8>PARAMETROS!$C$33,"",E8*F8) -> 5003.117 | H8: =IF($A8>PARAMETROS!$C$33,"",E8*PARAMETROS!$C$39) -> 754.26723 | I8: =IF($A8>PARAMETROS!$C$33,"",G8-H8) -> 4248.8497 | J8: =IF($A8>PARAMETROS!$C$33,"",PARAMETROS!$C$9*(1+PARAMETROS!$C$17)^(B8-1)) -> 30000 | K8: =IF($A8>PARAMETROS!$C$33,"",K7*(1+PARAMETROS!$C$36)) -> 26041.589 | L8: =IF($A8>PARAMETROS!$C$33,"",L7*(1+PARAMETROS!$C$37)*(1+M8)) -> 6608.1781 | M8: =IF($A8>PARAMETROS!$C$33,"",IF(C8<70,PARAMETROS!$C$40,IF(C8<75,PARAMETROS!$C$41,IF(C8<80,PARAMETROS!$C$42,IF(C8<85,PARAMETROS!$C$43,IF(C8<90,PARAMETROS!$C$44,PARAMETROS!$C$45)))))) -> 0.0024662698 | N8: =IF($A8>PARAMETROS!$C$33,"",K8+L8) -> 32649.767 | O8: =IF($A8>PARAMETROS!$C$33,"",I8+J8-N8) -> 1599.0826 | P8: =IF($A8>PARAMETROS!$C$33,"",MAX(E8+I8+J8-N8,0)) -> 1011430.5 | Q8: =IF($A8>PARAMETROS!$C$33,"",IF(P8<=0,"AGOTADO","OK")) -> OK
A9: =A8+1 -> 7 | B9: =IF($A9="","",ROUNDUP($A9/12,0)) -> 1 | C9: =IF($A9="","",PARAMETROS!$C$6+INT(($A9-1)/12)) -> 65 | D9: =IF($A9="","",MOD($A9-1,12)+1) -> 7 | E9: =IF($A9>PARAMETROS!$C$33,"",P8) -> 1011430.5 | F9: =IF($A9>PARAMETROS!$C$33,"",PARAMETROS!$C$38) -> 0.0049544082 | G9: =IF($A9>PARAMETROS!$C$33,"",E9*F9) -> 5011.0395 | H9: =IF($A9>PARAMETROS!$C$33,"",E9*PARAMETROS!$C$39) -> 755.46162 | I9: =IF($A9>PARAMETROS!$C$33,"",G9-H9) -> 4255.5778 | J9: =IF($A9>PARAMETROS!$C$33,"",PARAMETROS!$C$9*(1+PARAMETROS!$C$17)^(B9-1)) -> 30000 | K9: =IF($A9>PARAMETROS!$C$33,"",K8*(1+PARAMETROS!$C$36)) -> 26130.817 | L9: =IF($A9>PARAMETROS!$C$33,"",L8*(1+PARAMETROS!$C$37)*(1+M9)) -> 6650.6194 | M9: =IF($A9>PARAMETROS!$C$33,"",IF(C9<70,PARAMETROS!$C$40,IF(C9<75,PARAMETROS!$C$41,IF(C9<80,PARAMETROS!$C$42,IF(C9<85,PARAMETROS!$C$43,IF(C9<90,PARAMETROS!$C$44,PARAMETROS!$C$45)))))) -> 0.0024662698 | N9: =IF($A9>PARAMETROS!$C$33,"",K9+L9) -> 32781.436 | O9: =IF($A9>PARAMETROS!$C$33,"",I9+J9-N9) -> 1474.1417 | P9: =IF($A9>PARAMETROS!$C$33,"",MAX(E9+I9+J9-N9,0)) -> 1012904.6 | Q9: =IF($A9>PARAMETROS!$C$33,"",IF(P9<=0,"AGOTADO","OK")) -> OK
A10: =A9+1 -> 8 | B10: =IF($A10="","",ROUNDUP($A10/12,0)) -> 1 | C10: =IF($A10="","",PARAMETROS!$C$6+INT(($A10-1)/12)) -> 65 | D10: =IF($A10="","",MOD($A10-1,12)+1) -> 8 | E10: =IF($A10>PARAMETROS!$C$33,"",P9) -> 1012904.6 | F10: =IF($A10>PARAMETROS!$C$33,"",PARAMETROS!$C$38) -> 0.0049544082 | G10: =IF($A10>PARAMETROS!$C$33,"",E10*F10) -> 5018.343 | H10: =IF($A10>PARAMETROS!$C$33,"",E10*PARAMETROS!$C$39) -> 756.5627 | I10: =IF($A10>PARAMETROS!$C$33,"",G10-H10) -> 4261.7803 | J10: =IF($A10>PARAMETROS!$C$33,"",PARAMETROS!$C$9*(1+PARAMETROS!$C$17)^(B10-1)) -> 30000 | K10: =IF($A10>PARAMETROS!$C$33,"",K9*(1+PARAMETROS!$C$36)) -> 26220.35 | L10: =IF($A10>PARAMETROS!$C$33,"",L9*(1+PARAMETROS!$C$37)*(1+M10)) -> 6693.3332 | M10: =IF($A10>PARAMETROS!$C$33,"",IF(C10<70,PARAMETROS!$C$40,IF(C10<75,PARAMETROS!$C$41,IF(C10<80,PARAMETROS!$C$42,IF(C10<85,PARAMETROS!$C$43,IF(C10<90,PARAMETROS!$C$44,PARAMETROS!$C$45)))))) -> 0.0024662698 | N10: =IF($A10>PARAMETROS!$C$33,"",K10+L10) -> 32913.683 | O10: =IF($A10>PARAMETROS!$C$33,"",I10+J10-N10) -> 1348.0969 | P10: =IF($A10>PARAMETROS!$C$33,"",MAX(E10+I10+J10-N10,0)) -> 1014252.7 | Q10: =IF($A10>PARAMETROS!$C$33,"",IF(P10<=0,"AGOTADO","OK")) -> OK
A11: =A10+1 -> 9 | B11: =IF($A11="","",ROUNDUP($A11/12,0)) -> 1 | C11: =IF($A11="","",PARAMETROS!$C$6+INT(($A11-1)/12)) -> 65 | D11: =IF($A11="","",MOD($A11-1,12)+1) -> 9 | E11: =IF($A11>PARAMETROS!$C$33,"",P10) -> 1014252.7 | F11: =IF($A11>PARAMETROS!$C$33,"",PARAMETROS!$C$38) -> 0.0049544082 | G11: =IF($A11>PARAMETROS!$C$33,"",E11*F11) -> 5025.022 | H11: =IF($A11>PARAMETROS!$C$33,"",E11*PARAMETROS!$C$39) -> 757.56962 | I11: =IF($A11>PARAMETROS!$C$33,"",G11-H11) -> 4267.4524 | J11: =IF($A11>PARAMETROS!$C$33,"",PARAMETROS!$C$9*(1+PARAMETROS!$C$17)^(B11-1)) -> 30000 | K11: =IF($A11>PARAMETROS!$C$33,"",K10*(1+PARAMETROS!$C$36)) -> 26310.19 | L11: =IF($A11>PARAMETROS!$C$33,"",L10*(1+PARAMETROS!$C$37)*(1+M11)) -> 6736.3214 | M11: =IF($A11>PARAMETROS!$C$33,"",IF(C11<70,PARAMETROS!$C$40,IF(C11<75,PARAMETROS!$C$41,IF(C11<80,PARAMETROS!$C$42,IF(C11<85,PARAMETROS!$C$43,IF(C11<90,PARAMETROS!$C$44,PARAMETROS!$C$45)))))) -> 0.0024662698 | N11: =IF($A11>PARAMETROS!$C$33,"",K11+L11) -> 33046.512 | O11: =IF($A11>PARAMETROS!$C$33,"",I11+J11-N11) -> 1220.9406 | P11: =IF($A11>PARAMETROS!$C$33,"",MAX(E11+I11+J11-N11,0)) -> 1015473.7 | Q11: =IF($A11>PARAMETROS!$C$33,"",IF(P11<=0,"AGOTADO","OK")) -> OK
A12: =A11+1 -> 10 | B12: =IF($A12="","",ROUNDUP($A12/12,0)) -> 1 | C12: =IF($A12="","",PARAMETROS!$C$6+INT(($A12-1)/12)) -> 65 | D12: =IF($A12="","",MOD($A12-1,12)+1) -> 10 | E12: =IF($A12>PARAMETROS!$C$33,"",P11) -> 1015473.7 | F12: =IF($A12>PARAMETROS!$C$33,"",PARAMETROS!$C$38) -> 0.0049544082 | G12: =IF($A12>PARAMETROS!$C$33,"",E12*F12) -> 5031.071 | H12: =IF($A12>PARAMETROS!$C$33,"",E12*PARAMETROS!$C$39) -> 758.48157 | I12: =IF($A12>PARAMETROS!$C$33,"",G12-H12) -> 4272.5895 | J12: =IF($A12>PARAMETROS!$C$33,"",PARAMETROS!$C$9*(1+PARAMETROS!$C$17)^(B12-1)) -> 30000 | K12: =IF($A12>PARAMETROS!$C$33,"",K11*(1+PARAMETROS!$C$36)) -> 26400.338 | L12: =IF($A12>PARAMETROS!$C$33,"",L11*(1+PARAMETROS!$C$37)*(1+M12)) -> 6779.5856 | M12: =IF($A12>PARAMETROS!$C$33,"",IF(C12<70,PARAMETROS!$C$40,IF(C12<75,PARAMETROS!$C$41,IF(C12<80,PARAMETROS!$C$42,IF(C12<85,PARAMETROS!$C$43,IF(C12<90,PARAMETROS!$C$44,PARAMETROS!$C$45)))))) -> 0.0024662698 | N12: =IF($A12>PARAMETROS!$C$33,"",K12+L12) -> 33179.924 | O12: =IF($A12>PARAMETROS!$C$33,"",I12+J12-N12) -> 1092.6654 | P12: =IF($A12>PARAMETROS!$C$33,"",MAX(E12+I12+J12-N12,0)) -> 1016566.3 | Q12: =IF($A12>PARAMETROS!$C$33,"",IF(P12<=0,"AGOTADO","OK")) -> OK
A13: =A12+1 -> 11 | B13: =IF($A13="","",ROUNDUP($A13/12,0)) -> 1 | C13: =IF($A13="","",PARAMETROS!$C$6+INT(($A13-1)/12)) -> 65 | D13: =IF($A13="","",MOD($A13-1,12)+1) -> 11 | E13: =IF($A13>PARAMETROS!$C$33,"",P12) -> 1016566.3 | F13: =IF($A13>PARAMETROS!$C$33,"",PARAMETROS!$C$38) -> 0.0049544082 | G13: =IF($A13>PARAMETROS!$C$33,"",E13*F13) -> 5036.4845 | H13: =IF($A13>PARAMETROS!$C$33,"",E13*PARAMETROS!$C$39) -> 759.29771 | I13: =IF($A13>PARAMETROS!$C$33,"",G13-H13) -> 4277.1868 | J13: =IF($A13>PARAMETROS!$C$33,"",PARAMETROS!$C$9*(1+PARAMETROS!$C$17)^(B13-1)) -> 30000 | K13: =IF($A13>PARAMETROS!$C$33,"",K12*(1+PARAMETROS!$C$36)) -> 26490.795 | L13: =IF($A13>PARAMETROS!$C$33,"",L12*(1+PARAMETROS!$C$37)*(1+M13)) -> 6823.1278 | M13: =IF($A13>PARAMETROS!$C$33,"",IF(C13<70,PARAMETROS!$C$40,IF(C13<75,PARAMETROS!$C$41,IF(C13<80,PARAMETROS!$C$42,IF(C13<85,PARAMETROS!$C$43,IF(C13<90,PARAMETROS!$C$44,PARAMETROS!$C$45)))))) -> 0.0024662698 | N13: =IF($A13>PARAMETROS!$C$33,"",K13+L13) -> 33313.923 | O13: =IF($A13>PARAMETROS!$C$33,"",I13+J13-N13) -> 963.26373 | P13: =IF($A13>PARAMETROS!$C$33,"",MAX(E13+I13+J13-N13,0)) -> 1017529.6 | Q13: =IF($A13>PARAMETROS!$C$33,"",IF(P13<=0,"AGOTADO","OK")) -> OK
A14: =A13+1 -> 12 | B14: =IF($A14="","",ROUNDUP($A14/12,0)) -> 1 | C14: =IF($A14="","",PARAMETROS!$C$6+INT(($A14-1)/12)) -> 65 | D14: =IF($A14="","",MOD($A14-1,12)+1) -> 12 | E14: =IF($A14>PARAMETROS!$C$33,"",P13) -> 1017529.6 | F14: =IF($A14>PARAMETROS!$C$33,"",PARAMETROS!$C$38) -> 0.0049544082 | G14: =IF($A14>PARAMETROS!$C$33,"",E14*F14) -> 5041.2569 | H14: =IF($A14>PARAMETROS!$C$33,"",E14*PARAMETROS!$C$39) -> 760.01719 | I14: =IF($A14>PARAMETROS!$C$33,"",G14-H14) -> 4281.2397 | J14: =IF($A14>PARAMETROS!$C$33,"",PARAMETROS!$C$9*(1+PARAMETROS!$C$17)^(B14-1)) -> 30000 | K14: =IF($A14>PARAMETROS!$C$33,"",K13*(1+PARAMETROS!$C$36)) -> 26581.562 | L14: =IF($A14>PARAMETROS!$C$33,"",L13*(1+PARAMETROS!$C$37)*(1+M14)) -> 6866.9496 | M14: =IF($A14>PARAMETROS!$C$33,"",IF(C14<70,PARAMETROS!$C$40,IF(C14<75,PARAMETROS!$C$41,IF(C14<80,PARAMETROS!$C$42,IF(C14<85,PARAMETROS!$C$43,IF(C14<90,PARAMETROS!$C$44,PARAMETROS!$C$45)))))) -> 0.0024662698 | N14: =IF($A14>PARAMETROS!$C$33,"",K14+L14) -> 33448.512 | O14: =IF($A14>PARAMETROS!$C$33,"",I14+J14-N14) -> 832.72802 | P14: =IF($A14>PARAMETROS!$C$33,"",MAX(E14+I14+J14-N14,0)) -> 1018362.3 | Q14: =IF($A14>PARAMETROS!$C$33,"",IF(P14<=0,"AGOTADO","OK")) -> OK
A15: =A14+1 -> 13 | B15: =IF($A15="","",ROUNDUP($A15/12,0)) -> 2 | C15: =IF($A15="","",PARAMETROS!$C$6+INT(($A15-1)/12)) -> 66 | D15: =IF($A15="","",MOD($A15-1,12)+1) -> 1 | E15: =IF($A15>PARAMETROS!$C$33,"",P14) -> 1018362.3 | F15: =IF($A15>PARAMETROS!$C$33,"",PARAMETROS!$C$38) -> 0.0049544082 | G15: =IF($A15>PARAMETROS!$C$33,"",E15*F15) -> 5045.3826 | H15: =IF($A15>PARAMETROS!$C$33,"",E15*PARAMETROS!$C$39) -> 760.63918 | I15: =IF($A15>PARAMETROS!$C$33,"",G15-H15) -> 4284.7434 | J15: =IF($A15>PARAMETROS!$C$33,"",PARAMETROS!$C$9*(1+PARAMETROS!$C$17)^(B15-1)) -> 31182 | K15: =IF($A15>PARAMETROS!$C$33,"",K14*(1+PARAMETROS!$C$36)) -> 26672.64 | L15: =IF($A15>PARAMETROS!$C$33,"",L14*(1+PARAMETROS!$C$37)*(1+M15)) -> 6911.0528 | M15: =IF($A15>PARAMETROS!$C$33,"",IF(C15<70,PARAMETROS!$C$40,IF(C15<75,PARAMETROS!$C$41,IF(C15<80,PARAMETROS!$C$42,IF(C15<85,PARAMETROS!$C$43,IF(C15<90,PARAMETROS!$C$44,PARAMETROS!$C$45)))))) -> 0.0024662698 | N15: =IF($A15>PARAMETROS!$C$33,"",K15+L15) -> 33583.693 | O15: =IF($A15>PARAMETROS!$C$33,"",I15+J15-N15) -> 1883.0506 | P15: =IF($A15>PARAMETROS!$C$33,"",MAX(E15+I15+J15-N15,0)) -> 1020245.4 | Q15: =IF($A15>PARAMETROS!$C$33,"",IF(P15<=0,"AGOTADO","OK")) -> OK
... A722: =A721+1 -> 720 | B722: =IF($A722="","",ROUNDUP($A722/12,0)) -> 60 | C722: =IF($A722="","",PARAMETROS!$C$6+INT(($A722-1)/12)) -> 124 | D722: =IF($A722="","",MOD($A722-1,12)+1) -> 12 | E722: =IF($A722>PARAMETROS!$C$33,"",P721) | F722: =IF($A722>PARAMETROS!$C$33,"",PARAMETROS!$C$38) | G722: =IF($A722>PARAMETROS!$C$33,"",E722*F722) | H722: =IF($A722>PARAMETROS!$C$33,"",E722*PARAMETROS!$C$39) | I722: =IF($A722>PARAMETROS!$C$33,"",G722-H722) | J722: =IF($A722>PARAMETROS!$C$33,"",PARAMETROS!$C$9*(1+PARAMETROS!$C$17)^(B722-1)) | K722: =IF($A722>PARAMETROS!$C$33,"",K721*(1+PARAMETROS!$C$36)) | L722: =IF($A722>PARAMETROS!$C$33,"",L721*(1+PARAMETROS!$C$37)*(1+M722)) | M722: =IF($A722>PARAMETROS!$C$33,"",IF(C722<70,PARAMETROS!$C$40,IF(C722<75,PARAMETROS!$C$41,IF(C722<80,PARAMETROS!$C$42,IF(C722<85,PARAMETROS!$C$43,IF(C722<90,PARAMETROS!$C$44,PARAMETROS!$C$45)))))) | N722: =IF($A722>PARAMETROS!$C$33,"",K722+L722) | O722: =IF($A722>PARAMETROS!$C$33,"",I722+J722-N722) | P722: =IF($A722>PARAMETROS!$C$33,"",MAX(E722+I722+J722-N722,0)) | Q722: =IF($A722>PARAMETROS!$C$33,"",IF(P722<=0,"AGOTADO","OK"))

Sheet RESUMEN
B2: RESUMEN DEL MODELO
B4: DATOS DEL HORIZONTE
B5: Edad inicial | C5: =PARAMETROS!C6 -> 65
B6: Edad final | C6: =PARAMETROS!C7 -> 95
B7: Meses proyectados | C7: =PARAMETROS!C33 -> 360
B8: Capital inicial | C8: =PARAMETROS!C8 -> 1000000
B9: Pensión inicial | C9: =PARAMETROS!C9 -> 30000
B10: Gasto inicial | C10: =PARAMETROS!C10 -> 32000
B12: RESULTADOS AL FINAL DEL HORIZONTE
B13: Pensión mensual final | C13: =INDEX(AMORTIZACION!$J$3:$J$722,PARAMETROS!C33) -> 92006.798
B14: Gasto mensual total final | C14: =INDEX(AMORTIZACION!$N$3:$N$722,PARAMETROS!C33) -> 128373.69
B15: Gasto médico mensual final | C15: =INDEX(AMORTIZACION!$L$3:$L$722,PARAMETROS!C33) -> 40968.822
B16: % del gasto que es médico (final) | C16: =C15/C14 -> 0.31913722
B17: Saldo al final del horizonte | C17: =INDEX(AMORTIZACION!$P$3:$P$722,PARAMETROS!C33) -> 0
B19: ¿SE AGOTA EL PATRIMONIO?
B20: Indicador | C20: =IF(ISNUMBER(MATCH("AGOTADO",AMORTIZACION!$Q$3:$Q$722,0)),"NO ALCANZA — se agota antes","SI ALCANZA hasta la edad final") -> NO ALCANZA — se agota antes
B21: Edad de agotamiento | C21: =IFERROR(INDEX(AMORTIZACION!$C$3:$C$722,MATCH("AGOTADO",AMORTIZACION!$Q$3:$Q$722,0)),"No se agota en el horizonte") -> 82
B22: Mes de agotamiento (dentro del horizonte) | C22: =IFERROR(INDEX(AMORTIZACION!$A$3:$A$722,MATCH("AGOTADO",AMORTIZACION!$Q$3:$Q$722,0)),"N/A") -> 210
B24: PREGUNTAS 7 Y 8 — CAPITAL / PENSIÓN NECESARIOS
B25: Estas preguntas (capital inicial mínimo para llegar a los 95 con saldo ≥ 0, o pensión inicial mínima para que $1,000,000 alcancen) requieren una búsqueda iterativa (goal seek), no una fórmula cerrada, porque el gasto médico compuesto con aging no tiene solución algebraica simple. Cómo resolverlas en Excel: 1) Ve a Datos > Análisis Y si > Buscar objetivo. 2) 'Definir la celda': RESUMEN!C17 (Saldo al final del horizonte). 3) 'Con el valor': 0 4) 'Para cambiar la celda': PARAMETROS!C8 (capital inicial) o PARAMETROS!C9 (pensión inicial). Excel encontrará el valor exacto iterando el modelo de 360 meses.
B31: GRÁFICAS
B32: Nota: las gráficas usan el rango por defecto (360 meses, escenario 65→95). Si cambias el horizonte de forma importante, ajusta el rango de datos de la gráfica (clic derecho > Seleccionar datos).
